[
  {
    "subject": "rus",
    "block": "mutaxassislik",
    "topic": "Fonetika",
    "question": "Rus tilida nechta unli harf mavjud?",
    "options": ["6", "10", "33", "21"],
    "answer": 1,
    "explanation": "Rus tilida 10 ta unli harf (bukva) bor: а, е, ё, и, о, у, ы, э, ю, я."
  },
  {
    "subject": "rus",
    "block": "mutaxassislik",
    "topic": "Fonetika",
    "question": "Rus tilida nechta unli tovush mavjud?",
    "options": ["6", "10", "33", "42"],
    "answer": 0,
    "explanation": "Rus tilida faqat 6 ta unli tovush (zvuk) bor: [а], [о], [у], [э], [и], [ы]."
  },
  {
    "subject": "rus",
    "block": "mutaxassislik",
    "topic": "Fonetika",
    "question": "Rus alifbosida jami nechta harf bor?",
    "options": ["32", "34", "33", "30"],
    "answer": 2,
    "explanation": "Zamonaviy rus alifbosida jami 33 ta harf mavjud."
  },
  {
    "subject": "rus",
    "block": "mutaxassislik",
    "topic": "Fonetika",
    "question": "Qaysi harflar doim qattiq undosh tovushlarni bildiradi?",
    "options": ["ж, ш, ц", "ч, щ, й", "б, в, г", "п, ф, к"],
    "answer": 0,
    "explanation": "Rus tilida [ж], [ш], [ц] tovushlari har doim qattiq talaffuz qilinadi."
  },
  {
    "subject": "rus",
    "block": "mutaxassislik",
    "topic": "Fonetika",
    "question": "Qaysi harflar doim yumshoq undosh tovushlarni bildiradi?",
    "options": ["ж, ш, ц", "д, т, з", "м, н, л", "ч, щ, й"],
    "answer": 3,
    "explanation": "Rus tilida [ч'], [щ'], [й'] tovushlari har doim yumshoq hisoblanadi."
  },
  {
    "subject": "rus",
    "block": "mutaxassislik",
    "topic": "Fonetika",
    "question": "Rus tilida nechta undosh harf bor?",
    "options": ["20", "21", "33", "10"],
    "answer": 1,
    "explanation": "Rus alifbosida jami 21 ta undosh harf mavjud."
  },
  {
    "subject": "rus",
    "block": "mutaxassislik",
    "topic": "Fonetika",
    "question": "Qaysi qatordagi harflar so'z boshida ikkita tovush bildiradi?",
    "options": ["а, о, у, э", "и, ы, э, а", "е, ё, ю, я", "б, в, г, д"],
    "answer": 2,
    "explanation": "Е, ё, ю, я harflari so'z boshida, unlidan so'ng va ayirish/yumshatish belgilaridan keyin 2 ta tovushni (й+unli) bildiradi."
  },
  {
    "subject": "rus",
    "block": "mutaxassislik",
    "topic": "Fonetika",
    "question": "Jufti yo'q jarangli undoshlar (sonorlar) qaysilar?",
    "options": ["й, л, м, н, р", "х, ц, ч, щ", "б, в, г, д, ж, з", "п, ф, к, т, ш, с"],
    "answer": 0,
    "explanation": "Й, л, м, н, р — sonor undoshlar bo'lib, ularning jarangsiz jufti yo'q."
  },
  {
    "subject": "rus",
    "block": "mutaxassislik",
    "topic": "Fonetika",
    "question": "Jufti yo'q jarangsiz undoshlar qaysi qatorda to'g'ri ko'rsatilgan?",
    "options": ["й, л, м, н, р", "х, ц, ч, щ", "ж, ш, ц, ч", "б, д, г, з"],
    "answer": 1,
    "explanation": "Х, ц, ч, щ undoshlari doim jarangsiz bo'lib, ularning jarangli jufti mavjud emas."
  },
  {
    "subject": "rus",
    "block": "mutaxassislik",
    "topic": "Fonetika",
    "question": "Ayirish va yumshatish belgilari (ъ va ь) qanday xususiyatga ega?",
    "options": ["Doim qattiq talaffuz qilinadi", "Doim yumshoq talaffuz qilinadi", "Hech qanday tovushni bildirmaydi", "Unli tovushlarni bildiradi"],
    "answer": 2,
    "explanation": "Ъ va Ь belgilari o'ziga xos tovushga ega emas, faqat yonidagi harflarning talaffuzini o'zgartiradi yoki ajratadi."
  },
  {
    "subject": "rus",
    "block": "mutaxassislik",
    "topic": "Fonetika",
    "question": "Rus tilida urg'u (udareniye) qanday xususiyatga ega?",
    "options": ["Faqat birinchi bo'g'inga tushadi", "Erkin va o'zgaruvchan", "Faqat oxirgi bo'g'inga tushadi", "So'zdagi o'rnini hech qachon o'zgartirmaydi"],
    "answer": 1,
    "explanation": "Rus tilida urg'u erkin, ya'ni turli bo'g'inlarga tushishi mumkin va so'z o'zgarganda o'rnini o'zgartirishi mumkin."
  },
  {
    "subject": "rus",
    "block": "mutaxassislik",
    "topic": "Fonetika",
    "question": "Qaysi unli harf hech qachon so'z boshida kelmaydi?",
    "options": ["э", "а", "о", "ы"],
    "answer": 3,
    "explanation": "'Ы' harfi bilan boshlanadigan so'zlar rus tilida asosan mavjud emas."
  },
  {
    "subject": "rus",
    "block": "mutaxassislik",
    "topic": "Fonetika",
    "question": "So'z oxiridagi jarangli undoshlar qanday talaffuz qilinadi?",
    "options": ["Jarangsizlanadi", "Jarangliligini saqlab qoladi", "Tushib qoladi", "Ikkilanib talaffuz qilinadi"],
    "answer": 0,
    "explanation": "Qoida bo'yicha so'z oxiridagi jarangli undosh jarangsiz talaffuz qilinadi."
  },
  {
    "subject": "rus",
    "block": "mutaxassislik",
    "topic": "Fonetika",
    "question": "Bo'g'in ajratish qoidasiga ko'ra so'zdagi bo'g'inlar soni nimaga bog'liq?",
    "options": ["Undosh tovushlar soniga", "So'zning uzunligiga", "Urg'u tushishiga", "Unli tovushlar soniga"],
    "answer": 3,
    "explanation": "So'zda nechta unli tovush bo'lsa, shuncha bo'g'in bo'ladi."
  },
  {
    "subject": "rus",
    "block": "mutaxassislik",
    "topic": "Fonetika",
    "question": "Juft jarangli-jarangsiz undoshlar nechta?",
    "options": ["5 juft", "6 juft", "7 juft", "10 juft"],
    "answer": 1,
    "explanation": "Rus tilida 6 juft jarangli-jarangsiz undoshlar mavjud: б-п, в-ф, г-к, д-т, ж-ш, з-с."
  },
  {
    "subject": "rus",
    "block": "mutaxassislik",
    "topic": "Morfologiya",
    "question": "Rus tilida otlar (существительные) nechta rodga bo'linadi?",
    "options": ["2", "4", "3", "Rodlarga bo'linmaydi"],
    "answer": 2,
    "explanation": "Rus tilida otlar uchta rodga ega: mujskoy, jenskiy va sredniy."
  },
  {
    "subject": "rus",
    "block": "mutaxassislik",
    "topic": "Morfologiya",
    "question": "Jonli otlar (одушевленные существительные) qaysi so'roqqa javob beradi?",
    "options": ["Кто?", "Что?", "Какой?", "Где?"],
    "answer": 0,
    "explanation": "Jonli otlar 'Кто?' (Kim?) so'rog'iga javob beradi."
  },
  {
    "subject": "rus",
    "block": "mutaxassislik",
    "topic": "Morfologiya",
    "question": "Jonsiz otlar qaysi so'roqqa javob beradi?",
    "options": ["Кто?", "Когда?", "Что?", "Как?"],
    "answer": 2,
    "explanation": "Jonsiz otlar (неодушевленные) 'Что?' (Nima?) so'rog'iga javob beradi."
  },
  {
    "subject": "rus",
    "block": "mutaxassislik",
    "topic": "Morfologiya",
    "question": "Rus tilida otlarning turlanishi (склонение) nechta guruhga bo'linadi?",
    "options": ["2", "4", "6", "3"],
    "answer": 3,
    "explanation": "Otlarning turlanishi 3 ta skloneniyaga bo'linadi."
  },
  {
    "subject": "rus",
    "block": "mutaxassislik",
    "topic": "Morfologiya",
    "question": "-а, -я bilan tugaydigan mujskoy va jenskiy rod otlari qaysi skloneniyaga kiradi?",
    "options": ["1-skloneniye", "2-skloneniye", "3-skloneniye", "Turlanmaydigan otlar"],
    "answer": 0,
    "explanation": "-a va -ya qo'shimchasi bilan tugaydigan otlar 1-skloneniyaga tegishli."
  },
  {
    "subject": "rus",
    "block": "mutaxassislik",
    "topic": "Morfologiya",
    "question": "-о, -е bilan tugaydigan sredniy rod va nol qo'shimchali mujskoy rod otlari qaysi skloneniyaga kiradi?",
    "options": ["1-skloneniye", "2-skloneniye", "3-skloneniye", "Turlanmaydigan otlar"],
    "answer": 1,
    "explanation": "Bular 2-skloneniyaga kiradi (masalan, окно, стол)."
  },
  {
    "subject": "rus",
    "block": "mutaxassislik",
    "topic": "Morfologiya",
    "question": "Yumshatish belgisi (ь) bilan tugaydigan jenskiy rod otlari qaysi turlanishga kiradi?",
    "options": ["1-skloneniye", "2-skloneniye", "Erkin turlanish", "3-skloneniye"],
    "answer": 3,
    "explanation": "Ь bilan tugaydigan jenskiy rod otlari 3-skloneniyaga kiradi (masalan, ночь, мышь)."
  },
  {
    "subject": "rus",
    "block": "mutaxassislik",
    "topic": "Morfologiya",
    "question": "Sifat (прилагательное) qaysi so'roqlarga javob beradi?",
    "options": ["Какой? Какая? Какое? Какие?", "Кто? Что?", "Что делать? Что сделать?", "Как? Где? Куда?"],
    "answer": 0,
    "explanation": "Sifat narsaning belgisini bildiradi va Какой? Чей? so'roqlariga javob beradi."
  },
  {
    "subject": "rus",
    "block": "mutaxassislik",
    "topic": "Morfologiya",
    "question": "Sifat ot bilan qaysi xususiyatlarda moslashadi?",
    "options": ["Faqat rodda", "Rod, son va kelishikda", "Faqat sonda", "Zamon va shaxsda"],
    "answer": 1,
    "explanation": "Sifat o'zi bog'lanib kelgan ot bilan rod, son va kelishik (padej)da moslashadi."
  },
  {
    "subject": "rus",
    "block": "mutaxassislik",
    "topic": "Morfologiya",
    "question": "Sanoq sonlar (количественные числительные) qaysi so'roqqa javob bo'ladi?",
    "options": ["Который?", "Какой?", "Чей?", "Сколько?"],
    "answer": 3,
    "explanation": "Sanoq sonlar miqdorni bildiradi va Сколько? (Qancha/Nechta) so'rog'iga javob beradi."
  },
  {
    "subject": "rus",
    "block": "mutaxassislik",
    "topic": "Morfologiya",
    "question": "Tartib sonlar (порядковые числительные) qanday so'roqqa javob beradi?",
    "options": ["Сколько?", "Какой? Который?", "Когда?", "Кого?"],
    "answer": 1,
    "explanation": "Tartib sonlar narsaning sanalish tartibini bildiradi va Какой? (Qaysi?), Который? (Nechanchi?) so'roqlariga javob bo'ladi."
  },
  {
    "subject": "rus",
    "block": "mutaxassislik",
    "topic": "Morfologiya",
    "question": "'Я, ты, он, она, мы, вы, они' olmoshlari qaysi turga kiradi?",
    "options": ["Egalik olmoshlari", "Ko'rsatish olmoshlari", "Kishilik olmoshlari", "O'zlik olmoshlari"],
    "answer": 2,
    "explanation": "Bular kishilik olmoshlari (личные местоимения) bo'lib, shaxsni bildiradi."
  },
  {
    "subject": "rus",
    "block": "mutaxassislik",
    "topic": "Morfologiya",
    "question": "Fe'lning qaysi shakllari zamon, shaxs va son bilan o'zgarmaydi?",
    "options": ["Hozirgi zamon shakli", "Infinitiv (noaniq shakl)", "O'tgan zamon shakli", "Kelasi zamon shakli"],
    "answer": 1,
    "explanation": "Infinitiv (начальная форма глагола) o'zgarmas shakldir va -ть, -ти, -чь bilan tugaydi."
  },
  {
    "subject": "rus",
    "block": "mutaxassislik",
    "topic": "Morfologiya",
    "question": "Fe'lning qaysi ko'rinishi (вид) harakatning natijasini va tugallanganligini bildiradi?",
    "options": ["Совершенный вид (Tugallangan)", "Несовершенный вид (Tugallanmagan)", "O'zlik nisbati", "Majhul nisbat"],
    "answer": 0,
    "explanation": "Sovershenniy vid 'что сделать?' so'rog'iga javob bo'lib, tugallangan harakatni bildiradi."
  },
  {
    "subject": "rus",
    "block": "mutaxassislik",
    "topic": "Morfologiya",
    "question": "O'tgan zamon fe'llari (прошедшее время) nimalarga qarab o'zgaradi?",
    "options": ["Shaxs va son", "Faqat shaxs", "O'zgarmaydi", "Rod va son"],
    "answer": 3,
    "explanation": "O'tgan zamonda fe'llar shaxsga qarab o'zgarmaydi, faqat rod va songa qarab o'zgaradi."
  },
  {
    "subject": "rus",
    "block": "mutaxassislik",
    "topic": "Morfologiya",
    "question": "Ravish (наречие) qanday so'z turkumi hisoblanadi?",
    "options": ["Faqat kelishik bilan o'zgaruvchi", "O'zgarmas so'z turkumi", "Rod va sonda o'zgaruvchi", "Zamon bo'yicha o'zgaruvchi"],
    "answer": 1,
    "explanation": "Ravish o'zgarmas so'z turkumi bo'lib, turlanmaydi va tuslanmaydi."
  },
  {
    "subject": "rus",
    "block": "mutaxassislik",
    "topic": "Morfologiya",
    "question": "Predlog (предлог) qanday vazifani bajaradi?",
    "options": ["Yangi so'z yasash", "Harakatni ifodalash", "So'zlarni bir-biriga bog'lash", "Gap bo'laklarini ajratish"],
    "answer": 2,
    "explanation": "Predlog (ko'makchi) gapdagi ism, olmosh yoki sonlarni boshqa so'zlar bilan bog'lash uchun xizmat qiladi."
  },
  {
    "subject": "rus",
    "block": "mutaxassislik",
    "topic": "Morfologiya",
    "question": "Qaysi kelishik (padej) predlogsiz qo'llanilmaydi?",
    "options": ["Именительный (Bosh)", "Дательный (Jo'nalish)", "Винительный (Tushum)", "Предложный (O'rin-payt)"],
    "answer": 3,
    "explanation": "Predlojniy padej har doim predlog (в, на, о, об) bilan birga qo'llaniladi."
  },
  {
    "subject": "rus",
    "block": "mutaxassislik",
    "topic": "Morfologiya",
    "question": "Именительный падеж (Bosh kelishik) so'roqlari qaysilar?",
    "options": ["Кого? Чего?", "Кто? Что?", "Кому? Чему?", "Кем? Чем?"],
    "answer": 1,
    "explanation": "Imenitelniy padejning asosiy so'roqlari 'Кто?' (Kim?) va 'Что?' (Nima?)."
  },
  {
    "subject": "rus",
    "block": "mutaxassislik",
    "topic": "Morfologiya",
    "question": "Rus tilida nechta kelishik (padej) mavjud?",
    "options": ["6 ta", "5 ta", "4 ta", "7 ta"],
    "answer": 0,
    "explanation": "Rus tilida 6 ta kelishik bor: именительный, родительный, дательный, винительный, творительный, предложный."
  },
  {
    "subject": "rus",
    "block": "mutaxassislik",
    "topic": "Sintaksis",
    "question": "Gapning bosh bo'laklari (главные члены предложения) qaysilar?",
    "options": ["Дополнение и обстоятельство", "Определение и дополнение", "Подлежащее и сказуемое", "Сказуемое и обстоятельство"],
    "answer": 2,
    "explanation": "Gapning grammatik asosi ega va kesimdan iborat bo'ladi."
  },
  {
    "subject": "rus",
    "block": "mutaxassislik",
    "topic": "Sintaksis",
    "question": "Ega (подлежащее) odatda qaysi kelishikda bo'ladi?",
    "options": ["Родительный (Qaratqich)", "Винительный (Tushum)", "Дательный (Jo'nalish)", "Именительный (Bosh)"],
    "answer": 3,
    "explanation": "Ega doimo bosh kelishik (Кто? Что?) shaklida keladi."
  },
  {
    "subject": "rus",
    "block": "mutaxassislik",
    "topic": "Sintaksis",
    "question": "Kesim (сказуемое) nimanı ifodalaydi va asosan qaysi so'z turkumi bilan ifodalanadi?",
    "options": ["Eganing harakati yoki holatini (Fe'l bilan)", "Predmetning belgisini (Sifat bilan)", "Harakatning o'rnini (Ravish bilan)", "Predmetning miqdorini (Son bilan)"],
    "answer": 0,
    "explanation": "Kesim eganing nima qilayotganini yoki qanday holatdaligini bildiradi va asosan fe'l orqali ifodalanadi."
  },
  {
    "subject": "rus",
    "block": "mutaxassislik",
    "topic": "Sintaksis",
    "question": "To'ldiruvchi (дополнение) qanday so'roqlarga javob beradi?",
    "options": ["Именительный padej so'roqlariga", "Kosvenniy padej so'roqlariga", "Где? Куда? Откуда? so'roqlariga", "Какой? Чей? so'roqlariga"],
    "answer": 1,
    "explanation": "To'ldiruvchi kosvenniy (vositali) kelishiklar so'roqlariga javob beradi."
  },
  {
    "subject": "rus",
    "block": "mutaxassislik",
    "topic": "Sintaksis",
    "question": "Aniqlovchi (определение) ostiga qanday chiziq chiziladi?",
    "options": ["Bir to'g'ri chiziq", "Ikki to'g'ri chiziq", "Shtrixli chiziq", "To'lqinli chiziq"],
    "answer": 3,
    "explanation": "Sintaktik tahlilda aniqlovchi (Какой? Чей?) ostiga to'lqinli chiziq chiziladi."
  },
  {
    "subject": "rus",
    "block": "mutaxassislik",
    "topic": "Sintaksis",
    "question": "Hol (обстоятельство) qanday so'roqlarga javob beradi?",
    "options": ["Кто? Что?", "Где? Когда? Куда? Откуда? Почему? Как?", "Кого? Чего? Кому? Чему?", "Какой? Какая? Какое?"],
    "answer": 1,
    "explanation": "Hol harakatning o'rni, payti, sababi, maqsadi va tarzini bildirib, shu savollarga javob bo'ladi."
  },
  {
    "subject": "rus",
    "block": "mutaxassislik",
    "topic": "Sintaksis",
    "question": "Prostoye (oddiy) gapning slojnoye (qo'shma) gapdan farqi nimada?",
    "options": ["Faqat bosh bo'laklardan iborat bo'ladi", "Gap bo'laklari bo'lmaydi", "Grammatik asosi bitta bo'ladi", "So'zlar soni kam bo'ladi"],
    "answer": 2,
    "explanation": "Oddiy gap bitta grammatik asosdan iborat bo'ladi, qo'shma gapda esa ikkita va undan ortiq asos bo'ladi."
  },
  {
    "subject": "rus",
    "block": "mutaxassislik",
    "topic": "Sintaksis",
    "question": "Сложносочиненное предложение (Bog'langan qo'shma gap) qanday qismlardan iborat?",
    "options": ["Teng huquqli mustaqil qismlardan", "Bosh va ergash gaplardan", "Faqat egalarsiz gaplardan", "Faqat undalmalardan"],
    "answer": 0,
    "explanation": "Bog'langan qo'shma gapning qismlari grammatik jihatdan teng huquqli bo'lib, сочинительные soyuzlar bilan bog'lanadi."
  },
  {
    "subject": "rus",
    "block": "mutaxassislik",
    "topic": "Sintaksis",
    "question": "Сложноподчиненное предложение (Ergash gapli qo'shma gap) xususiyati nima?",
    "options": ["Barcha qismlari mustaqil bo'ladi", "Faqat bitta eituvchi asosga ega", "Uyushiq bo'laklarga boy bo'ladi", "Bosh gap va unga tobe bo'lgan ergash gapdan iborat"],
    "answer": 3,
    "explanation": "Ergash gapli qo'shma gap bitta bosh va unga tobe bo'lgan ergash gapdan iborat bo'ladi."
  },
  {
    "subject": "rus",
    "block": "mutaxassislik",
    "topic": "Sintaksis",
    "question": "Undalma (обращение) gap bo'lagi bo'la oladimi?",
    "options": ["Ha, asosan ega bo'ladi", "Yo'q, gap bo'lagi bo'lmaydi", "Ha, doim to'ldiruvchi bo'ladi", "Ha, asosan hol bo'ladi"],
    "answer": 1,
    "explanation": "Undalma hech qanday gap bo'lagi vazifasini bajarmaydi."
  },
  {
    "subject": "rus",
    "block": "mutaxassislik",
    "topic": "Sintaksis",
    "question": "Kirish so'zlar (вводные слова) yozuvda qanday ajratiladi?",
    "options": ["Qo'shtirnoq bilan", "Qavs bilan", "Vergul bilan", "Tire bilan"],
    "answer": 2,
    "explanation": "Kirish so'zlar yozuvda odatda vergul bilan ajratiladi."
  },
  {
    "subject": "rus",
    "block": "mutaxassislik",
    "topic": "Sintaksis",
    "question": "Bir xil so'roqqa javob beruvchi va bir xil gap bo'lagiga bog'lanib kelgan bo'laklar qanday nomlanadi?",
    "options": ["Вводные слова (Kirish so'zlar)", "Однородные члены (Uyushiq bo'laklar)", "Обращение (Undalma)", "Сложные слова (Qo'shma so'zlar)"],
    "answer": 1,
    "explanation": "Bular gapning bir jinsli (uyushiq) bo'laklari deb ataladi."
  },
  {
    "subject": "rus",
    "block": "mutaxassislik",
    "topic": "Sintaksis",
    "question": "Предложение (Gap) ifoda maqsadiga ko'ra qanday turlarga bo'linadi?",
    "options": ["Oddiy va qo'shma", "Yoyiq va yig'iq", "Shaxsli va shaxssiz", "Darak, so'roq va buyruq"],
    "answer": 3,
    "explanation": "Gaplar maqsadiga ko'ra darak, so'roq va buyruq turlariga bo'linadi."
  },
  {
    "subject": "rus",
    "block": "mutaxassislik",
    "topic": "Sintaksis",
    "question": "Бессоюзное сложное предложение (Bog'lovchisiz qo'shma gap) nima bilan bog'lanadi?",
    "options": ["Faqat ohang (интонация) bilan", "Союзы (bog'lovchilar) orqali", "Предлоги (ko'makchilar) orqali", "Faqat tire orqali"],
    "answer": 0,
    "explanation": "Bog'lovchisiz qo'shma gap qismlari faqat ma'no va ohang orqali bog'lanadi."
  },
  {
    "subject": "rus",
    "block": "mutaxassislik",
    "topic": "Sintaksis",
    "question": "Ikkinchi darajali bo'laklar ishtirok etgan gap qanday nomlanadi?",
    "options": ["Нераспространенное (Yig'iq gap)", "Простое (Oddiy gap)", "Распространенное (Yoyiq gap)", "Сложное (Qo'shma gap)"],
    "answer": 2,
    "explanation": "Agar gapda bosh bo'laklardan tashqari ikkinchi darajali bo'lak qatnashsa, bu yoyiq (распространенное) gap bo'ladi."
  }
]
